pandas_util/__init__.py
pandas_util-0.0.1.dist-info/METADATA
pandas_util-0.0.1.dist-info/WHEEL
pandas_util-0.0.1.dist-info/top_level.txt
pandas_util-0.0.1.dist-info/RECORD
